{"type":"FeatureCollection","features":[{"type":"Feature","properties":{"Name":"Oregon State Office Building","Contributor":"Lyzi Diamond","Reason":"Work"},"geometry":{"type":"Point","coordinates":[-122.6579761505127,45.52822320885938]}}]}